azure/mgmt/carbonoptimization/__init__.py
azure/mgmt/carbonoptimization/_client.py
azure/mgmt/carbonoptimization/_configuration.py
azure/mgmt/carbonoptimization/_patch.py
azure/mgmt/carbonoptimization/_version.py
azure/mgmt/carbonoptimization/py.typed
azure/mgmt/carbonoptimization/_utils/__init__.py
azure/mgmt/carbonoptimization/_utils/model_base.py
azure/mgmt/carbonoptimization/_utils/serialization.py
azure/mgmt/carbonoptimization/aio/__init__.py
azure/mgmt/carbonoptimization/aio/_client.py
azure/mgmt/carbonoptimization/aio/_configuration.py
azure/mgmt/carbonoptimization/aio/_patch.py
azure/mgmt/carbonoptimization/aio/operations/__init__.py
azure/mgmt/carbonoptimization/aio/operations/_operations.py
azure/mgmt/carbonoptimization/aio/operations/_patch.py
azure/mgmt/carbonoptimization/models/__init__.py
azure/mgmt/carbonoptimization/models/_enums.py
azure/mgmt/carbonoptimization/models/_models.py
azure/mgmt/carbonoptimization/models/_patch.py
azure/mgmt/carbonoptimization/operations/__init__.py
azure/mgmt/carbonoptimization/operations/_operations.py
azure/mgmt/carbonoptimization/operations/_patch.py
azure_mgmt_carbonoptimization-1.0.0.dist-info/LICENSE
azure_mgmt_carbonoptimization-1.0.0.dist-info/METADATA
azure_mgmt_carbonoptimization-1.0.0.dist-info/WHEEL
azure_mgmt_carbonoptimization-1.0.0.dist-info/top_level.txt
azure_mgmt_carbonoptimization-1.0.0.dist-info/RECORD
